LICENSE.md
MANIFEST.in
README.md
dynamic_extras_require.txt
dynamic_install_requires.txt
quicklib_incorporated.v2.5.zip
quicklib_setup_from_yml.py
epic/logging/__init__.py
epic/logging/__version__.py
epic/logging/logger.py
epic/logging/logregator.py
epic/logging/tests/__init__.py
epic/logging/tests/test_logger.py
epic_logging.egg-info/PKG-INFO
epic_logging.egg-info/SOURCES.txt
epic_logging.egg-info/dependency_links.txt
epic_logging.egg-info/requires.txt
epic_logging.egg-info/top_level.txt