Metadata-Version: 2.1
Name: epic-logging
Version: 1.0.5
Summary: Easy logging with multiprocessing support
Home-page: https://github.com/Cybereason/epic-logging
Author: Uri Sternfeld, Assaf Ben-David, Yonatan Perry
License: MIT License
Classifier: Development Status :: 4 - Beta
Classifier: Intended Audience :: Developers
Classifier: Operating System :: POSIX :: Linux
Classifier: Operating System :: MacOS :: MacOS X
Classifier: Operating System :: Microsoft :: Windows
Classifier: Programming Language :: Python :: 3 :: Only
Classifier: Programming Language :: Python :: 3.10
Requires-Python: >=3.10
License-File: LICENSE.md
